odoo/addons/base_multi_company/README.rst
odoo/addons/base_multi_company/__init__.py
odoo/addons/base_multi_company/__manifest__.py
odoo/addons/base_multi_company/hooks.py
odoo/addons/base_multi_company/i18n/base_multi_company.pot
odoo/addons/base_multi_company/i18n/es.po
odoo/addons/base_multi_company/i18n/es_AR.po
odoo/addons/base_multi_company/i18n/fr.po
odoo/addons/base_multi_company/i18n/hr.po
odoo/addons/base_multi_company/i18n/it.po
odoo/addons/base_multi_company/i18n/nl_NL.po
odoo/addons/base_multi_company/i18n/pt.po
odoo/addons/base_multi_company/i18n/pt_BR.po
odoo/addons/base_multi_company/i18n/tr.po
odoo/addons/base_multi_company/i18n/zh_CN.po
odoo/addons/base_multi_company/models/__init__.py
odoo/addons/base_multi_company/models/base.py
odoo/addons/base_multi_company/models/multi_company_abstract.py
odoo/addons/base_multi_company/readme/CONTRIBUTORS.md
odoo/addons/base_multi_company/readme/DESCRIPTION.md
odoo/addons/base_multi_company/readme/DEVELOPER.rst
odoo/addons/base_multi_company/static/description/icon.png
odoo/addons/base_multi_company/static/description/index.html
odoo/addons/base_multi_company/tests/__init__.py
odoo/addons/base_multi_company/tests/multi_company_abstract_tester.py
odoo/addons/base_multi_company/tests/test_multi_company_abstract.py
odoo_addon_base_multi_company-18.0.1.1.0.dist-info/METADATA
odoo_addon_base_multi_company-18.0.1.1.0.dist-info/WHEEL
odoo_addon_base_multi_company-18.0.1.1.0.dist-info/top_level.txt
odoo_addon_base_multi_company-18.0.1.1.0.dist-info/RECORD
