Metadata-Version: 2.1
Name: odoo-addon-base_multi_company
Version: 18.0.1.1.0
Requires-Python: >=3.10
Requires-Dist: odoo==18.0.*
Summary: Provides a base for adding multi-company support to models.
Home-page: https://github.com/OCA/multi-company
License: LGPL-3
Author: ACSONE SA/NV, LasLabs, Tecnativa, Odoo Community Association (OCA)
Author-email: support@odoo-community.org
Classifier: Programming Language :: Python
Classifier: Framework :: Odoo
Classifier: Framework :: Odoo :: 18.0
Classifier: License :: OSI Approved :: GNU Lesser General Public License v3 (LGPLv3)
Classifier: Development Status :: 5 - Production/Stable
